venture/__init__.py
venture/__main__.py
venture/libs/__init__.py
venture/libs/config_editor.py
venture/libs/file_prep.py
venture/libs/globals/__init__.py
venture/libs/globals/global_functions.py
venture/libs/globals/global_objects.py
venture/templates/python/LICENSE
venture/templates/python/setup.py
venture_tools-2020.10.27.dist-info/LICENSE
venture_tools-2020.10.27.dist-info/METADATA
venture_tools-2020.10.27.dist-info/WHEEL
venture_tools-2020.10.27.dist-info/entry_points.txt
venture_tools-2020.10.27.dist-info/top_level.txt
venture_tools-2020.10.27.dist-info/RECORD
