Metadata-Version: 2.1
Name: venture-tools
Version: 2020.10.27
Summary: a CLI tool to initialize a new project
Home-page: https://github.com/murmuur-git/venture.git
Author: murmuur
Author-email: murmuur@protonmail.com
License: UNKNOWN
Download-URL: https://github.com/murmuur-git/venture/archive/v2020.10.26-alpha.2.tar.gz
Platform: UNKNOWN
Requires-Python: >=3.6
Requires-Dist: requests (>=2.24.0)
